README.md
setup.py
sebaprinttest/__init__.py
sebaprinttest.egg-info/PKG-INFO
sebaprinttest.egg-info/SOURCES.txt
sebaprinttest.egg-info/dependency_links.txt
sebaprinttest.egg-info/top_level.txt
sebaprinttest/calculus/__init__.py
sebaprinttest/calculus/calculus.py
sebaprinttest/calculus/printother.py
sebaprinttest/printme/__init__.py
sebaprinttest/printme/printme.py