Metadata-Version: 2.1
Name: sebaprinttest
Version: 0.0.2
Summary: Pypi test
Home-page: https://github.com/sebastiancuba/sebaprinttest
Author: Seba
Author-email: seba@gmail.com
License: GPL 3.0
Platform: UNKNOWN
Classifier: Programming Language :: Python :: 3
Classifier: License :: OSI Approved :: GNU General Public License v3 or later (GPLv3+)
Requires-Python: >=3.5
